facial_vision_agent/__init__.py
facial_vision_agent/agent.py
facial_vision_agent/llm_client.py
facial_vision_agent/prompts.py
facial_vision_agent/utils.py
facial_vision_agent-1.0.0.dist-info/licenses/LICENSE
facial_vision_agent-1.0.0.dist-info/METADATA
facial_vision_agent-1.0.0.dist-info/WHEEL
facial_vision_agent-1.0.0.dist-info/top_level.txt
facial_vision_agent-1.0.0.dist-info/RECORD
