Metadata-Version: 2.4
Name: facial-vision-agent
Version: 1.0.0
Summary: Specialized agent for facial and hair analysis
Home-page: https://github.com/msalsas/facial-vision-agent
Author: Manolo Salsas
Author-email: manolez@gmail.com
License: MIT
Classifier: Development Status :: 3 - Alpha
Classifier: Intended Audience :: Developers
Classifier: Programming Language :: Python :: 3
Classifier: Programming Language :: Python :: 3.8
Classifier: Programming Language :: Python :: 3.9
Classifier: Programming Language :: Python :: 3.10
Classifier: Programming Language :: Python :: 3.11
Requires-Python: >=3.8
License-File: LICENSE
Requires-Dist: agent-core-framework>=0.1.6
Requires-Dist: opencv-python>=4.8.0
Requires-Dist: requests>=2.28.0
Provides-Extra: dev
Requires-Dist: pytest>=7.0.0; extra == "dev"
Requires-Dist: black>=23.0.0; extra == "dev"
Dynamic: license-file
